moneyx/__init__.py
moneyx/bulk.py
moneyx/core.py
moneyx/currency.py
moneyx/exceptions.py
moneyx/py.typed
moneyx/rounding.py
moneyx/serialization.py
moneyx-0.1.1.dist-info/licenses/LICENSE
moneyx-0.1.1.dist-info/METADATA
moneyx-0.1.1.dist-info/WHEEL
moneyx-0.1.1.dist-info/top_level.txt
moneyx-0.1.1.dist-info/RECORD
