Metadata-Version: 2.4
Name: moneyx
Version: 0.1.1
Summary: Precise and extensible library for handling money in Python
Author: devAbreu
Maintainer: devAbreu
License: MIT
Project-URL: Homepage, https://github.com/devAbreu/moneyx
Project-URL: Documentation, https://moneyx.readthedocs.io/en/latest/
Project-URL: Bug Tracker, https://github.com/devAbreu/moneyx/issues
Project-URL: Source Code, https://github.com/devAbreu/moneyx
Project-URL: Changelog, https://github.com/devAbreu/moneyx/blob/main/CHANGELOG.md
Keywords: money,currency,finance,accounting,decimal,monetary,precision
Classifier: Development Status :: 4 - Beta
Classifier: Intended Audience :: Developers
Classifier: Intended Audience :: Financial and Insurance Industry
Classifier: License :: OSI Approved :: MIT License
Classifier: Operating System :: OS Independent
Classifier: Programming Language :: Python :: 3
Classifier: Programming Language :: Python :: 3.8
Classifier: Programming Language :: Python :: 3.9
Classifier: Programming Language :: Python :: 3.10
Classifier: Programming Language :: Python :: 3.11
Classifier: Programming Language :: Python :: 3.12
Classifier: Topic :: Office/Business :: Financial
Classifier: Topic :: Software Development :: Libraries :: Python Modules
Classifier: Typing :: Typed
Requires-Python: >=3.8
License-File: LICENSE
Requires-Dist: Babel>=2.12.0
Requires-Dist: typing-extensions>=4.0.0; python_version < "3.10"
Provides-Extra: dev
Requires-Dist: black>=23.1.0; extra == "dev"
Requires-Dist: isort>=5.12.0; extra == "dev"
Requires-Dist: mypy>=1.0.1; extra == "dev"
Requires-Dist: ruff>=0.0.54; extra == "dev"
Requires-Dist: pre-commit>=3.3.0; extra == "dev"
Requires-Dist: bandit>=1.7.5; extra == "dev"
Provides-Extra: test
Requires-Dist: pytest>=7.3.1; extra == "test"
Requires-Dist: pytest-cov>=4.1.0; extra == "test"
Requires-Dist: pytest-benchmark>=4.0.0; extra == "test"
Requires-Dist: hypothesis>=6.70.0; extra == "test"
Requires-Dist: pytest-xdist>=3.3.0; extra == "test"
Provides-Extra: docs
Requires-Dist: sphinx>=7.0.0; extra == "docs"
Requires-Dist: sphinx-rtd-theme>=1.2.0; extra == "docs"
Requires-Dist: sphinx-autodoc-typehints>=1.23.0; extra == "docs"
Requires-Dist: myst-parser>=2.0.0; extra == "docs"
Requires-Dist: sphinxcontrib-napoleon>=0.7; extra == "docs"
Provides-Extra: all
Requires-Dist: moneyx[dev,docs,test]; extra == "all"
Dynamic: license-file
